[{
  "_id": {
    "$oid": "5f529a476f55451d8cb78cfe"
  },
  "Name": "Project1",
  "TotalEstimate": 16,
  "createdAt": {
    "$date": "2020-09-04T19:49:27.300Z"
  },
  "updatedAt": {
    "$date": "2020-09-04T19:49:27.300Z"
  },
  "__v": 0
},{
  "_id": {
    "$oid": "5f529ba06f55451d8cb78cff"
  },
  "Name": "Project2",
  "TotalEstimate": 4,
  "createdAt": {
    "$date": "2020-09-04T19:55:12.462Z"
  },
  "updatedAt": {
    "$date": "2020-09-04T19:55:12.462Z"
  },
  "__v": 0
},{
  "_id": {
    "$oid": "5f529bac6f55451d8cb78d00"
  },
  "Name": "Project3",
  "TotalEstimate": 3,
  "createdAt": {
    "$date": "2020-09-04T19:55:24.688Z"
  },
  "updatedAt": {
    "$date": "2020-09-04T19:55:24.688Z"
  },
  "__v": 0
},{
  "_id": {
    "$oid": "5f529bbc6f55451d8cb78d01"
  },
  "Name": "Project4",
  "TotalEstimate": 4,
  "createdAt": {
    "$date": "2020-09-04T19:55:40.814Z"
  },
  "updatedAt": {
    "$date": "2020-09-04T19:55:40.814Z"
  },
  "__v": 0
},{
  "_id": {
    "$oid": "5f529be06f55451d8cb78d02"
  },
  "Name": "Project5",
  "TotalEstimate": 4,
  "createdAt": {
    "$date": "2020-09-04T19:56:16.146Z"
  },
  "updatedAt": {
    "$date": "2020-09-04T19:56:16.146Z"
  },
  "__v": 0
},{
  "_id": {
    "$oid": "5f529cb86f55451d8cb78d0d"
  },
  "Name": "Project6",
  "TotalEstimate": 2,
  "createdAt": {
    "$date": "2020-09-04T19:59:52.124Z"
  },
  "updatedAt": {
    "$date": "2020-09-04T19:59:52.124Z"
  },
  "__v": 0
}]